cli.py
renderer.py
minecraft_avatar_generator-0.1.0.dist-info/licenses/LICENSE
minecraft_avatar_generator-0.1.0.dist-info/METADATA
minecraft_avatar_generator-0.1.0.dist-info/WHEEL
minecraft_avatar_generator-0.1.0.dist-info/entry_points.txt
minecraft_avatar_generator-0.1.0.dist-info/top_level.txt
minecraft_avatar_generator-0.1.0.dist-info/RECORD
