Metadata-Version: 2.4
Name: minecraft-avatar-generator
Version: 0.1.0
Summary: A command-line utility to generate 2D and 3D isometric renders of Minecraft skins from a player's username, UUID, or skin hash.
Author-email: soisyhpe <soisyhpe@gmail.com>
License-Expression: MIT
Classifier: Development Status :: 4 - Beta
Classifier: Environment :: Console
Classifier: Intended Audience :: Developers
Classifier: Operating System :: OS Independent
Classifier: Programming Language :: Python :: 3
Classifier: Programming Language :: Python :: 3.13
Classifier: Topic :: Games/Entertainment
Classifier: Topic :: Multimedia :: Graphics :: 3D Rendering
Classifier: Topic :: Utilities
Requires-Python: >=3.13
License-File: LICENSE
Requires-Dist: pillow>=12.0.0
Requires-Dist: numpy>=1.26.0
Requires-Dist: attrs>=23.0.0
Provides-Extra: dev
Requires-Dist: build; extra == "dev"
Requires-Dist: twine; extra == "dev"
Dynamic: license-file
